rust_argpartition-0.1.0.dist-info/METADATA
rust_argpartition-0.1.0.dist-info/WHEEL
rust_argpartition-0.1.0.dist-info/licenses/LICENSE.md
polars_argpartition/__init__.py
polars_argpartition/README.md
polars_argpartition/_internal.pyi
polars_argpartition/typing.py
polars_argpartition/_internal.abi3.so
rust_argpartition-0.1.0.dist-info/RECORD
